redis_collections/__init__.py
redis_collections/base.py
redis_collections/dicts.py
redis_collections/lists.py
redis_collections/sets.py
redis_collections/sortedsets.py
redis_collections/syncable.py
redis_collections-0.13.0.dist-info/LICENSE
redis_collections-0.13.0.dist-info/METADATA
redis_collections-0.13.0.dist-info/WHEEL
redis_collections-0.13.0.dist-info/top_level.txt
redis_collections-0.13.0.dist-info/RECORD
