Metadata-Version: 2.1
Name: redis-collections
Version: 0.13.0
Summary: Set of basic Python collections backed by Redis.
Home-page: https://github.com/redis-collections/redis-collections
Author: Honza Javorek
Author-email: mail@honzajavorek.cz
License: ISC
Keywords: redis,persistence
Classifier: Development Status :: 5 - Production/Stable
Classifier: Intended Audience :: Developers
Classifier: License :: OSI Approved :: ISC License (ISCL)
Classifier: Programming Language :: Python
Classifier: Programming Language :: Python :: 3
Classifier: Topic :: Database
Requires-Python: >=3.8
License-File: LICENSE
Requires-Dist: redis (<6.0.0,>=4.0.0)
